grahamcracker/__init__.py
grahamcracker/_convert.py
grahamcracker/_fast_conversion.py
grahamcracker/_field_classes.py
grahamcracker/_field_conversion.py
grahamcracker/_load_dataclass.py
grahamcracker/_schema_classes.py
grahamcracker/_settings_classes.py
grahamcracker/_version.py
grahamcracker-1.0.1.dist-info/LICENSE
grahamcracker-1.0.1.dist-info/METADATA
grahamcracker-1.0.1.dist-info/WHEEL
grahamcracker-1.0.1.dist-info/top_level.txt
grahamcracker-1.0.1.dist-info/RECORD
